deepath/__init__.py
deepath/cli.py
deepath/env.py
deepath/resolver.py
deepath-0.1.3.dist-info/licenses/LICENSE
deepath-0.1.3.dist-info/METADATA
deepath-0.1.3.dist-info/WHEEL
deepath-0.1.3.dist-info/entry_points.txt
deepath-0.1.3.dist-info/top_level.txt
deepath-0.1.3.dist-info/RECORD
