Metadata-Version: 2.4
Name: deepath
Version: 0.1.3
Summary: Reliable path resolution for Python apps, even in frozen environments like PyInstaller.
Author-email: Lounes ALLIOUI <la.lounas.allioui.pro@gmail.com>
License: MIT
Requires-Python: >=3.7
License-File: LICENSE
Dynamic: license-file
